google_api_helpers/__init__.py
google_api_helpers/auth.py
google_api_helpers/drive.py
google_api_helpers/email.py
google_api_helpers/sheets.py
google_api_helpers/youtube.py
src/__init__.py
src/auth.py
src/drive.py
src/email.py
src/sheets.py
test/__init__.py
test/constants.py
test/test_drive.py
test/test_email.py
test/test_sheets.py
test/utils/__init__.py
test/utils/auth.py
test/utils/drive.py
apatterson189_google_api_helpers-0.1.5.dist-info/LICENSE
apatterson189_google_api_helpers-0.1.5.dist-info/METADATA
apatterson189_google_api_helpers-0.1.5.dist-info/WHEEL
apatterson189_google_api_helpers-0.1.5.dist-info/top_level.txt
apatterson189_google_api_helpers-0.1.5.dist-info/RECORD
